morse_code/__init__.py
morse_code/constants.py
morse_code/converter.py
morse_code/dash.mp3
morse_code/dot.mp3
morse_code/minion_mode.py
src/morse_code/__init__.py
src/morse_code/constants.py
src/morse_code/converter.py
src/morse_code/dash.mp3
src/morse_code/dot.mp3
src/morse_code/minion_mode.py
morse_code_converter-1.1.dist-info/METADATA
morse_code_converter-1.1.dist-info/WHEEL
morse_code_converter-1.1.dist-info/entry_points.txt
morse_code_converter-1.1.dist-info/top_level.txt
morse_code_converter-1.1.dist-info/RECORD
